{
  "decks": [
    {
      "name": "React Router",
      "description": "React Router is a collection of navigational components that compose declaratively with your application.",
      "id": 2
    },
    {
      "name": "deck",
      "description": "decky deck",
      "id": 5
    },
    {
      "name": "test after many changes",
      "description": "does it still work?",
      "id": 6
    }
  ],
  "cards": [
    {
      "front": "What does <Switch> do?",
      "back": "Renders the first matching child <Route> ",
      "deckId": 2,
      "id": 5
    },
    {
      "front": "card card",
      "back": "cardy card",
      "deckId": 5,
      "id": 30
    },
    {
      "front": "card 2: card harder",
      "back": "the back",
      "deckId": 5,
      "id": 31
    },
    {
      "front": "yes!",
      "back": "SUCCESS!",
      "deckId": 6,
      "id": 32
    },
    {
      "front": "card 3: revenge of the cards",
      "back": "oof\n",
      "deckId": 5,
      "id": 33
    }
  ]
}